graphviz_bin/stub.cpython-37m-x86_64-linux-gnu.so
graphviz_bin/dot
graphviz_bin/__init__.py
pygraphviz_bin.libs/libltdl-1138dc32.so.7.3.2
pygraphviz_bin-0.0.1.2255565199.dist-info/WHEEL
pygraphviz_bin-0.0.1.2255565199.dist-info/top_level.txt
pygraphviz_bin-0.0.1.2255565199.dist-info/METADATA
pygraphviz_bin-0.0.1.2255565199.dist-info/RECORD
pygraphviz_bin-0.0.1.2255565199.dist-info/LICENSE
