Metadata-Version: 2.1
Name: pygraphviz-bin
Version: 0.0.1.2255565199
Summary: Pre-compiled GraphViz wrapped in Python
Home-page: https://github.com/mballance/pygraphviz-bin
Author: Matthew Ballance
Author-email: matt.ballance@gmail.com
License: Apache 2.0
Keywords: GraphViz,Dot
Platform: UNKNOWN
License-File: LICENSE
